predict_backend/__init__.py
predict_backend-0.1.0.dist-info/METADATA
predict_backend-0.1.0.dist-info/WHEEL
predict_backend-0.1.0.dist-info/top_level.txt
predict_backend-0.1.0.dist-info/RECORD
