Metadata-Version: 2.4
Name: predict-backend
Version: 0.1.0
Summary: Short description of your package
Author-email: Justin Gantenberg <justin@virtualitics.com>
Project-URL: Homepage, https://www.virtualitics.com
